quantities/__init__.py
quantities/acceleration.py
quantities/amount_of_heat.py
quantities/amount_of_substance.py
quantities/amount_of_substance_concentration.py
quantities/angular_acceleration.py
quantities/angular_velocity.py
quantities/area.py
quantities/capacitance.py
quantities/current_density.py
quantities/density.py
quantities/dynamic_viscosity.py
quantities/electric_charge.py
quantities/electric_conductance.py
quantities/electric_constant.py
quantities/electric_current.py
quantities/electric_field_strength.py
quantities/electric_potential_difference.py
quantities/electric_resistance.py
quantities/energy.py
quantities/energy_density.py
quantities/entropy.py
quantities/force.py
quantities/frequency.py
quantities/gradient_speed_position.py
quantities/gradient_temperature_position.py
quantities/heat_capacity.py
quantities/heat_flux_density.py
quantities/identity.py
quantities/inductance.py
quantities/length.py
quantities/luminous_intensity.py
quantities/magnetic_field_strength.py
quantities/magnetic_flux.py
quantities/magnetic_flux_density.py
quantities/magnetic_permeability.py
quantities/mass.py
quantities/mass_concentration.py
quantities/moment_of_force.py
quantities/plane_angle.py
quantities/power.py
quantities/quantity.py
quantities/quantity_type.py
quantities/radial_area.py
quantities/radial_length.py
quantities/solid_angle.py
quantities/specific_energy.py
quantities/specific_entropy.py
quantities/specific_heat_capacity.py
quantities/specific_volume.py
quantities/stress.py
quantities/surface_density.py
quantities/surface_tension.py
quantities/thermal_conductivity.py
quantities/thermodynamic_temperature.py
quantities/time.py
quantities/units.py
quantities/velocity.py
quantities/volume.py
quantities/wavenumber.py
quantities/work.py
Physical_Quantity_calculating-0.1.0.dist-info/LICENSE
Physical_Quantity_calculating-0.1.0.dist-info/METADATA
Physical_Quantity_calculating-0.1.0.dist-info/WHEEL
Physical_Quantity_calculating-0.1.0.dist-info/top_level.txt
Physical_Quantity_calculating-0.1.0.dist-info/RECORD
