Metadata-Version: 2.1
Name: Physical-Quantity-calculating
Version: 0.1.0
Summary: 
Home-page: UNKNOWN
Author: chenmich
Author-email: 403189920@qq.com
License: UNKNOWN
Platform: UNKNOWN
